pysp2/__init__.py
pysp2/io/__init__.py
pysp2/io/read_dat.py
pysp2/io/read_hk.py
pysp2/io/read_ini.py
pysp2/io/read_sp2b.py
pysp2/io/write_dat.py
pysp2/testing/__init__.py
pysp2/testing/sample_files.py
pysp2/testing/data/mosaossp2M1.00.20191216.000601.raw.20191216000000.ini
pysp2/testing/data/mosaossp2M1.00.20191216.130601.raw.20191216x193.sp2b
pysp2/testing/data/mosaossp2auxM1.00.20191217.010801.raw.20191216000000.hk
pysp2/util/DMTGlobals.py
pysp2/util/__init__.py
pysp2/util/deadtime.py
pysp2/util/leo_fit.py
pysp2/util/particle_properties.py
pysp2/util/peak_fit.py
pysp2/vis/__init__.py
pysp2/vis/data_editor.py
pysp2/vis/plot_wave.py
pysp2-1.7.0.dist-info/licenses/LICENSE
pysp2-1.7.0.dist-info/METADATA
pysp2-1.7.0.dist-info/WHEEL
pysp2-1.7.0.dist-info/top_level.txt
pysp2-1.7.0.dist-info/RECORD
