Metadata-Version: 2.4
Name: pysp2
Version: 1.7.0
Summary: Py-SP2
Home-page: 
Author: Bobby Jackson
Author-email: rjackson@anl.gov
License: BSD
Project-URL: Source, https://github.com/ARM-DOE/PySP2
Platform: Linux
Platform: Windows
Platform: OSX
License-File: LICENSE
Requires-Dist: pandas
Requires-Dist: numpy
Requires-Dist: scipy
Requires-Dist: xarray
Requires-Dist: act-atmos
Requires-Dist: xlrd
Requires-Dist: matplotlib
Dynamic: author
Dynamic: author-email
Dynamic: description
Dynamic: description-content-type
Dynamic: license
Dynamic: license-file
Dynamic: platform
Dynamic: project-url
Dynamic: requires-dist
Dynamic: summary
